topsis_mukul_102303463/__init__.py
topsis_mukul_102303463/topsis.py
topsis_mukul_102303463-0.0.0.dist-info/licenses/LICENSE
topsis_mukul_102303463-0.0.0.dist-info/METADATA
topsis_mukul_102303463-0.0.0.dist-info/WHEEL
topsis_mukul_102303463-0.0.0.dist-info/entry_points.txt
topsis_mukul_102303463-0.0.0.dist-info/top_level.txt
topsis_mukul_102303463-0.0.0.dist-info/RECORD
