Metadata-Version: 2.4
Name: Topsis-Mukul-102303463
Version: 0.0.0
Summary: TOPSIS implementation with CLI support
Author: Mukul
Author-email: mukulghai12@gmail.com
Requires-Python: >=3.7
License-File: LICENSE
Requires-Dist: pandas
Requires-Dist: numpy
Requires-Dist: openpyxl
Dynamic: author
Dynamic: author-email
Dynamic: description
Dynamic: description-content-type
Dynamic: license-file
Dynamic: requires-dist
Dynamic: requires-python
Dynamic: summary
